Evison/Evison.py
Evison/__init__.py
Evison/misc_functions.py
Evison-0.4.8.dist-info/LICENSE
Evison-0.4.8.dist-info/METADATA
Evison-0.4.8.dist-info/WHEEL
Evison-0.4.8.dist-info/top_level.txt
Evison-0.4.8.dist-info/RECORD
