Metadata-Version: 2.1
Name: Evison
Version: 0.4.8
Summary: Feature map visualization
Home-page: https://github.com/JonnesLin/Evison
Author: Jones Lin
Author-email: jonneslin@gmail.com
License: UNKNOWN
Platform: UNKNOWN
Classifier: Programming Language :: Python :: 3
Classifier: License :: OSI Approved :: MIT License
Classifier: Operating System :: OS Independent
Requires-Dist: torchviz
